beam/.DS_Store
beam/__init__.py
beam/_version.py
beam/algorithm/__init__.py
beam/algorithm/catboost_algorithm.py
beam/algorithm/catboost_consts.py
beam/algorithm/config.py
beam/algorithm/core_algorithm.py
beam/algorithm/group_expansion.py
beam/algorithm/neural_algorithm.py
beam/algorithm/sklearn_algorithm.py
beam/assistant/__init__.py
beam/assistant/assistant.py
beam/auto/__init__.py
beam/auto/auto.py
beam/auto/docker-tools/gracefull-pip.py
beam/auto/dockerfile-bash-entrypoint
beam/auto/dockerfile-simple-entrypoint
beam/auto/profiler.py
beam/auto/synchronous-server.py
beam/auto/utils.py
beam/base/__init__.py
beam/base/base_cache.py
beam/base/base_class.py
beam/base/beam_resource.py
beam/base/beam_url.py
beam/base/consts.py
beam/base/elements.py
beam/bayesian/__init__.py
beam/bayesian/config.py
beam/bayesian/core.py
beam/bayesian/experiment_schemas.py
beam/bayesian/hp_scheme.py
beam/bayesian/hpo_service.py
beam/bayesian/models.py
beam/concurrent/__init__.py
beam/concurrent/core.py
beam/concurrent/tasks.py
beam/concurrent/utils.py
beam/config/__init__.py
beam/config/configurations.py
beam/config/core_config.py
beam/config/deepspeed.py
beam/config/utils.py
beam/data/__init__.py
beam/data/beam_data.py
beam/data/beam_schema.py
beam/dataset/__init__.py
beam/dataset/sampler.py
beam/dataset/tabular_dataset.py
beam/dataset/universal_dataset.py
beam/dataset/variants.py
beam/distributed/__init__.py
beam/distributed/async_client.py
beam/distributed/async_server.py
beam/distributed/asyncio_dispatcher.py
beam/distributed/celery_dispatcher.py
beam/distributed/celery_worker.py
beam/distributed/pool_dispatcher.py
beam/distributed/ray_dispatcher.py
beam/distributed/resource.py
beam/distributed/utils.py
beam/docs/__init__.py
beam/docs/config.py
beam/docs/core.py
beam/docs/dsl2kql.py
beam/docs/elastic.py
beam/docs/elastic_configuration/docker-compose.yaml
beam/docs/elastic_configuration/logstash/pipeline/logstash.conf
beam/docs/elastic_configuration/run_elastic.sh
beam/docs/groupby.py
beam_ds-2.8.3.dist-info/LICENSE
beam_ds-2.8.3.dist-info/METADATA
beam_ds-2.8.3.dist-info/WHEEL
beam_ds-2.8.3.dist-info/RECORD
