Metadata-Version: 2.3
Name: beam-ds
Version: 2.8.3
Summary: Beam Datascience package
Author: Beam Maintainer
Author-email: author@example.com
Requires-Python: >=3.10
Classifier: License :: OSI Approved :: MIT License
Classifier: Operating System :: OS Independent
Classifier: Programming Language :: Python :: 3
Classifier: Programming Language :: Python :: 3.10
Classifier: Programming Language :: Python :: 3.11
Classifier: Programming Language :: Python :: 3.12
Classifier: Programming Language :: Python :: 3.13
Provides-Extra: serve
Requires-Dist: PyYAML
Requires-Dist: google-cloud-storage
Requires-Dist: joblib
Requires-Dist: kubernetes
Requires-Dist: loguru
Requires-Dist: pandas
Requires-Dist: pydantic (>=2.0)
Requires-Dist: requests
Requires-Dist: termcolor
Requires-Dist: tqdm
Requires-Dist: urllib3
Project-URL: Documentation, https://github.com/mlutils/beamds
Project-URL: Repository, https://github.com/mlutils/beamds
